metricsreport/__init__.py
metricsreport/custom_metrics.py
metricsreport/metricsreport.py
metricsreport-2025.7.23.dist-info/LICENSE
metricsreport-2025.7.23.dist-info/METADATA
metricsreport-2025.7.23.dist-info/WHEEL
metricsreport-2025.7.23.dist-info/RECORD
