Metadata-Version: 2.1
Name: metricsreport
Version: 2025.7.23
Summary: Generating reports on metrics for Machine Learning models
Home-page: https://github.com/Alex-Lekov/metricsreport
Author: Alex Lekov
Author-email: 11148364-AlexLekov@users.noreply.gitlab.com
Requires-Python: >=3.9,<4.0
Classifier: Programming Language :: Python :: 3
Classifier: Programming Language :: Python :: 3.9
Classifier: Programming Language :: Python :: 3.10
Classifier: Programming Language :: Python :: 3.11
Classifier: Programming Language :: Python :: 3.12
Requires-Dist: matplotlib (>=3.7.1,<4.0.0)
Requires-Dist: pandas (>=2.2.2,<3.0.0)
Requires-Dist: scikit-learn (>=1.3.0,<2.0.0)
Requires-Dist: scipy (>=1.13.0,<2.0.0)
Requires-Dist: seaborn (>=0.13.2,<0.14.0)
Project-URL: Repository, https://github.com/Alex-Lekov/metricsreport
